pifold_pytorch/__init__.py
pifold_pytorch/data.py
pifold_pytorch/pifold_pytorch.py
pifold_pytorch/train.py
pifold_pytorch-0.0.1.dist-info/METADATA
pifold_pytorch-0.0.1.dist-info/WHEEL
pifold_pytorch-0.0.1.dist-info/top_level.txt
pifold_pytorch-0.0.1.dist-info/RECORD
